MANIFEST.in
README.rst
setup.py
docs/HISTORY.txt
docs/INSTALL.txt
docs/LICENSE.GPL
docs/LICENSE.txt
rer/__init__.py
rer.fix13603.egg-info/PKG-INFO
rer.fix13603.egg-info/SOURCES.txt
rer.fix13603.egg-info/dependency_links.txt
rer.fix13603.egg-info/entry_points.txt
rer.fix13603.egg-info/namespace_packages.txt
rer.fix13603.egg-info/not-zip-safe
rer.fix13603.egg-info/requires.txt
rer.fix13603.egg-info/top_level.txt
rer/fix13603/__init__.py
rer/fix13603/configure.zcml
rer/fix13603/monkey.py
rer/fix13603/testing.py
rer/fix13603/tests/__init__.py
rer/fix13603/tests/test_patch.py