Metadata-Version: 1.1
Name: rer.fix13603
Version: 1.0.0
Summary: Patch for deletion by acquisition in Plone<4.3.3
Home-page: http://plone.org/products/rer.fix13603
Author: RedTurtle Technology
Author-email: sviluppoplone@redturtle.it
License: GPL
Keywords: plone fix delete acquisition
Platform: UNKNOWN
Classifier: Framework :: Plone
Classifier: Programming Language :: Python
Classifier: Framework :: Plone :: 4.0
Classifier: Framework :: Plone :: 4.1
Classifier: Framework :: Plone :: 4.2
Classifier: Programming Language :: Python
